LEA_CU.v
module LEA_CU(rst, clk, LCD_addr, star, sharp, chk_text, chk_key, star_out, sharp_out);
  input rst;
  input clk;
  output [2:0] LCD_addr;
  input star;
  input sharp;
  output chk_text;
  output chk_key;
  output star_out;
  output sharp_out;

  reg [2:0] LCD_addr;
  reg chk_text;
  reg chk_key;
  reg star_out;
  reg sharp_out;

  parameter [2:0] Start = 0, InputPlainText = 1, InputKey = 2, EncryptionSuccess = 3, ShowEncryptedText = 4, InputKey_decrypt = 5, DecryptSuccess = 6;
  reg [2:0] current_state, next_state;

  always @(posedge clk or posedge rst)
  begin: SYNCH
    if (rst == 1'b1)
       current_state <= Start;
    else
       current_state <= next_state;
  end

  always @(current_state or star or sharp)
  begin: COMBIN
     case (current_state)
        Start:
        begin
          if (star == 1'b1)
             begin
             next_state <= InputPlainText;
             end
          else if (sharp == 1'b1)
             begin
             next_state <= ShowEncryptedText;
             end
          else
             begin
             next_state <= Start;
             end
          LCD_addr <= 3'b000;
          star_out <= 1'b0;
          sharp_out <= 1'b0;
          chk_text <= 1'b0;
          chk_key <= 1'b0;

        end

        InputPlainText:
        begin
          if (star == 1'b0)
             begin
             next_state <= InputPlainText;
             end
          else if (star == 1'b1)
             begin
             next_state <= InputKey;
             end
          LCD_addr <= 3'b001;
          star_out <= 1'b1;
          sharp_out <= 1'b0;
          chk_text <= 1'b1;
          chk_key <= 1'b0;

        end

        InputKey:
        begin
          if (star == 1'b0)
             begin
             next_state <= InputKey;
             end
          else if (star == 1'b1)
             begin
             next_state <= EncryptionSuccess;
             end
          LCD_addr <= 3'b010;
          star_out <= 1'b0;
          sharp_out <= 1'b0;
          chk_text <= 1'b0;
          chk_key <= 1'b1;

        end

        EncryptionSuccess:
        begin
          if (star == 1'b0)
             begin
             next_state <= EncryptionSuccess;
             end
          else if (star == 1'b1)
             begin
             next_state <= Start;
             end
          LCD_addr <= 3'b011;
          star_out <= 1'b0;
          sharp_out <= 1'b0;
          chk_text <= 1'b0;
          chk_key <= 1'b0;

        end

        ShowEncryptedText:
        begin
          if (sharp == 1'b1)
             begin
             next_state <= InputKey_decrypt;
             end
          else if (sharp == 1'b0)
             begin
             next_state <= ShowEncryptedText;
             end
          LCD_addr <= 3'b100;
          star_out <= 1'b0;
          sharp_out <= 1'b1;
          chk_text <= 1'b0;
          chk_key <= 1'b0;

        end

        InputKey_decrypt:
        begin
          if (sharp == 1'b0)
             begin
             next_state <= InputKey_decrypt;
             end
          else if (sharp == 1'b1)
             begin
             next_state <= DecryptSuccess;
             end
          LCD_addr <= 3'b010;
          star_out <= 1'b0;
          sharp_out <= 1'b0;
          chk_text <= 1'b0;
          chk_key <= 1'b1;

        end

        DecryptSuccess:
        begin
          if (sharp == 1'b1)
             begin
             next_state <= Start;
             end
          else if (sharp == 1'b0)
             begin
             next_state <= DecryptSuccess;
             end
          LCD_addr <= 3'b101;
          star_out <= 1'b0;
          sharp_out <= 1'b0;
          chk_text <= 1'b0;
          chk_key <= 1'b0;

        end


        default:
          next_state <= Start;
     endcase
  end

endmodule

LEA_CU_tb.v
module LEA_CU_tb;

parameter DecryptSuccess = 6;
parameter EncryptionSuccess = 3;
parameter InputKey = 2;
parameter InputKey_decrypt = 5;
parameter InputPlainText = 1;
parameter ShowEncryptedText = 4;
parameter Start = 0;

wire [2:0] LCD_addr;
wire chk_key;
wire chk_text;
reg clk;
reg rst;
reg sharp;
wire sharp_out;
reg star;
wire star_out;

LEA_CU
 #(
  .DecryptSuccess(6),
  .EncryptionSuccess(3),
  .InputKey(2),
  .InputKey_decrypt(5),
  .InputPlainText(1),
  .ShowEncryptedText(4),
  .Start(0))
 U0 (
  .LCD_addr(LCD_addr),
  .chk_key(chk_key),
  .chk_text(chk_text),
  .clk(clk),
  .rst(rst),
  .sharp(sharp),
  .sharp_out(sharp_out),
  .star(star),
  .star_out(star_out));

  initial
  begin
    clk = 1'b0;
    #50 clk = 1'b1;
    #50 clk = 1'b0;
    #50 clk = 1'b1;
    #50 clk = 1'b0;
    #50 clk = 1'b1;
    #50 clk = 1'b0;
    #50 clk = 1'b1;
    #50 clk = 1'b0;
    #50 clk = 1'b1;
    #50 clk = 1'b0;
    #50 clk = 1'b1;
    #50 clk = 1'b0;
    #50 clk = 1'b1;
    #50 clk = 1'b0;
    #50 clk = 1'b1;
    #50 clk = 1'b0;
    #50 clk = 1'b1;
    #50 clk = 1'b0;
    #50 clk = 1'b1;
    #50 clk = 1'b0;
    #50 clk = 1'b1;
    #50 clk = 1'b0;
    #50 clk = 1'b1;
    #50 clk = 1'b0;
    #50 clk = 1'b1;
    #50 clk = 1'b0;
    #50 clk = 1'b1;
    #50 clk = 1'b0;
    #50 clk = 1'b1;
    #50 clk = 1'b0;
    #50 clk = 1'b1;
    #50 clk = 1'b0;
    #50 clk = 1'b1;
    #50 clk = 1'b0;
    #50 clk = 1'b1;
    #50 clk = 1'b0;
    #50 clk = 1'b1;
    #50 clk = 1'b0;
    #50 clk = 1'b1;
    #50 clk = 1'b0;
    #50 clk = 1'b1;
    #50 clk = 1'b0;
    #50 clk = 1'b1;
    #50 clk = 1'b0;
    #50 clk = 1'b1;
    #50 clk = 1'b0;
    #50 clk = 1'b1;
    #50 clk = 1'b0;
    #50 clk = 1'b1;
    #50 clk = 1'b0;
    #50 clk = 1'b1;
    #50 clk = 1'b0;
    #50 clk = 1'b1;
    #50 clk = 1'b0;
    #50 clk = 1'b1;
    #50 clk = 1'b0;
    #50 clk = 1'b1;
    #50 clk = 1'b0;
    #50 clk = 1'b1;
    #50 clk = 1'b0;
    #50 clk = 1'b1;
    #50 clk = 1'b0;
    #50 clk = 1'b1;
    #50 clk = 1'b0;
    #50 clk = 1'b1;
    #50 clk = 1'b0;
    #50 clk = 1'b1;
    #50 clk = 1'b0;
    #50 clk = 1'b1;
    #50 clk = 1'b0;
    #50 clk = 1'b1;
    #50 clk = 1'b0;
    #50 clk = 1'b1;
    #50 clk = 1'b0;
    #50 clk = 1'b1;
    #50 clk = 1'b0;
    #50 clk = 1'b1;
    #50 clk = 1'b0;
    #50 clk = 1'b1;
    #50 clk = 1'b0;
    #50 clk = 1'b1;
    #50 clk = 1'b0;
    #50 clk = 1'b1;
    #50 clk = 1'b0;
    #50 clk = 1'b1;
    #50 clk = 1'b0;
    #50 clk = 1'b1;
    #50 clk = 1'b0;
    #50 clk = 1'b1;
    #50 clk = 1'b0;
    #50 clk = 1'b1;
    #50 clk = 1'b0;
    #50 clk = 1'b1;
    #50 clk = 1'b0;
    #50 clk = 1'b1;
    #50 clk = 1'b0;
    #50 clk = 1'b1;
    #50 clk = 1'b0;
    #50 clk = 1'b1;
    #50 clk = 1'b0;
    #50 clk = 1'b1;
    #50 clk = 1'b0;
    #50 clk = 1'b1;
    #50 clk = 1'b0;
    #50 clk = 1'b1;
    #50 clk = 1'b0;
    #50 clk = 1'b1;
    #50 clk = 1'b0;
    #50 clk = 1'b1;
    #50 clk = 1'b0;
    #50 clk = 1'b1;
    #50 clk = 1'b0;
    #50 clk = 1'b1;
    #50 clk = 1'b0;
    #50 clk = 1'b1;
    #50 clk = 1'b0;
    #50 clk = 1'b1;
    #50 clk = 1'b0;
    #50 clk = 1'b1;
    #50 clk = 1'b0;
    #50 clk = 1'b1;
    #50 clk = 1'b0;
    #50 clk = 1'b1;
    #50 clk = 1'b0;
    #50 clk = 1'b1;
    #50 clk = 1'b0;
    #50 clk = 1'b1;
    #50 clk = 1'b0;
    #50 clk = 1'b1;
    #50 clk = 1'b0;
    #50 clk = 1'b1;
    #50 clk = 1'b0;
    #50 clk = 1'b1;
    #50 clk = 1'b0;
    #50 clk = 1'b1;
    #50 clk = 1'b0;
    #50 clk = 1'b1;
    #50 clk = 1'b0;
    #50 clk = 1'b1;
    #50 clk = 1'b0;
    #50 clk = 1'b1;
    #50 clk = 1'b0;
    #50 clk = 1'b1;
    #50 clk = 1'b0;
    #50 clk = 1'b1;
    #50 clk = 1'b0;
    #50 clk = 1'b1;
    #50 clk = 1'b0;
    #50 clk = 1'b1;
    #50 clk = 1'b0;
    #50 clk = 1'b1;
    #50 clk = 1'b0;
    #50 clk = 1'b1;
    #50 clk = 1'b0;
    #50 clk = 1'b1;
    #50 clk = 1'b0;
    #50 clk = 1'b1;
    #50 clk = 1'b0;
    #50 clk = 1'b1;
    #50 clk = 1'b0;
    #50 clk = 1'b1;
    #50 clk = 1'b0;
    #50 clk = 1'b1;
    #50 clk = 1'b0;
    #50 clk = 1'b1;
    #50 clk = 1'b0;
    #50 clk = 1'b1;
    #50 clk = 1'b0;
    #50 clk = 1'b1;
    #50 clk = 1'b0;
    #50 clk = 1'b1;
    #50 clk = 1'b0;
    #50 clk = 1'b1;
    #50 clk = 1'b0;
    #50 clk = 1'b1;
    #50 clk = 1'b0;
    #50 clk = 1'b1;
    #50 clk = 1'b0;
    #50 clk = 1'b1;
    #50 clk = 1'b0;
    #50 clk = 1'b1;
    #50 clk = 1'b0;
    #50 clk = 1'b1;
    #50 clk = 1'b0;
    #50 clk = 1'b1;
    #50 clk = 1'b0;
    #50 clk = 1'b1;
    #50 clk = 1'b0;
    #50 clk = 1'b1;
    #50 clk = 1'b0;
    #50 clk = 1'b1;
    #50 clk = 1'b0;
    #50 clk = 1'b1;
    #50 clk = 1'b0;
    #50 clk = 1'b1;
    #50 clk = 1'b0;
    #50 clk = 1'b1;
    #50 clk = 1'b0;
    #50 clk = 1'b1;
  end

  initial
  begin
    rst = 1'b1;
    #200 rst = 1'b0;
  end

  initial
  begin
    sharp = 1'b0;
    #1500 sharp = 1'b1;
    #100 sharp = 1'b0;
    #200 sharp = 1'b1;
    #100 sharp = 1'b0;
    #200 sharp = 1'b1;
    #100 sharp = 1'b0;
    #200 sharp = 1'b1;
    #100 sharp = 1'b0;
  end

  initial
  begin
    star = 1'b0;
    #300 star = 1'b1;
    #100 star = 1'b0;
    #200 star = 1'b1;
    #100 star = 1'b0;
    #200 star = 1'b1;
    #100 star = 1'b0;
    #200 star = 1'b1;
    #100 star = 1'b0;
  end

endmodule

_service/20191224045309_SimulateISim_jeonsoe_LEA_CU_tb/LEA_CU_tb.vcd
$date
   Tue Dec 24 04:53:14 2019
$end
$version
  P.15xf
$end
$timescale
  1ps
$end
$scope module LEA_CU_tb $end
$var wire 1 ! LCD_addr [2] $end
$var wire 1 " LCD_addr [1] $end
$var wire 1 # LCD_addr [0] $end
$var wire 1 $ chk_key $end
$var wire 1 % chk_text $end
$var wire 1 & sharp_out $end
$var wire 1 ' star_out $end
$var reg 1 ( clk $end
$var reg 1 ) rst $end
$var reg 1 * sharp $end
$var reg 1 + star $end
$upscope $end
$enddefinitions $end
#0
$dumpvars
x!
x$
x%
x&
x'
x#
x"
0(
1)
0*
0+
$end
#50000
0!
0$
0%
0&
0'
0#
0"
1(
#100000
0(
0)
#150000
1(
#200000
0(
#250000
1(
#300000
0(
1+
#350000
1(
#400000
0(
#450000
1(
#500000
0(
0+
#550000
1(
#600000
0(
#650000
1(
#700000
0(
#750000
1(
#800000
0(
1+
#850000
1(
#900000
0(
#950000
1(
#1000000
0(
#1050000
1(
#1100000
0(
#1150000
1(
#1200000
0(
0+
#1250000
1(
#1300000
0(
#1350000
1(
#1400000
0(
#1450000
1(
#1500000
0(
#1550000
1(
#1600000
0(
#1650000
1(
#1700000
0(
1+
#1750000
1(
#1800000
0(
#1850000
1(
#1900000
0(
#1950000
1(
#2000000
0(
#2050000
1(
#2100000
0(
#2150000
1(
#2200000
0(
0+
#2250000
1(
#2300000
0(
#2350000
1(
#2400000
0(
#2450000
1(
#2500000
0(
1*
#2550000
1(
#2600000
0(
#2650000
1(
#2700000
0(
#2750000
1(
#2800000
0(
#2850000
1(
#2900000
0(
0*
#2950000
1(
#3000000
0(
#3050000
1(
#3100000
0(
#3150000
1(
#3200000
0(
#3250000
1(
#3300000
0(
#3350000
1(
#3400000
0(
#3450000
1(
#3500000
0(
1*
#3550000
1(
#3600000
0(
#3650000
1(
#3700000
0(
#3750000
1(
#3800000
0(
#3850000
1(
#3900000
0(
#3950000
1(
#4000000
0(
0*
#4050000
1(
#4100000
0(
#4150000
1(
#4200000
0(
#4250000
1(
#4300000
0(
#4350000
1(
#4400000
0(
#4450000
1(
#4500000
0(
#4550000
1(
#4600000
0(
#4650000
1(
#4700000
0(
#4750000
1(
#4800000
0(
1*
#4850000
1(
#4900000
0(
#4950000
1(
#5000000
0(
#5050000
1(
#5100000
0(
#5150000
1(
#5200000
0(
#5250000
1(
#5300000
0(
0*
#5350000
1(
#5400000
0(
#5450000
1(
#5500000
0(
#5550000
1(
#5600000
0(
1+
#5650000
1(
#5700000
0(
#5750000
1(
#5800000
0(
#5850000
1(
#5900000
0(
#5950000
1(
#6000000
0(
#6050000
1(
#6100000
0(
#6150000
1(
#6200000
0(
0+
#6250000
1(
#6300000
0(
#6350000
1(
#6400000
0(
#6450000
1(
#6500000
0(
#6550000
1(
#6600000
0(
#6650000
1(
#6700000
0(
#6750000
1(
#6800000
0(
1+
#6850000
1(
#6900000
0(
#6950000
1(
#7000000
0(
#7050000
1(
#7100000
0(
#7150000
1(
#7200000
0(
#7250000
1(
#7300000
0(
0+
#7350000
1(
#7400000
0(
#7450000
1(
#7500000
0(
#7550000
1(
#7600000
0(
#7650000
1(
#7700000
0(
#7750000
1(
#7800000
0(
#7850000
1(
#7900000
0(
#7950000
1(
#8000000
0(
#8050000
1(
#8100000
0(
1+
#8150000
1(
#8200000
0(
#8250000
1(
#8300000
0(
#8350000
1(
#8400000
0(
#8450000
1(
#8500000
0(
0+
#8550000
1(
#8600000
0(
1*
#8650000
1(
#8700000
0(
#8750000
1(
#8800000
0(
#8850000
1(
#8900000
0(
0*
#8950000
1(
#9000000
0(
#9050000
1(
#9100000
0(
1*
#9150000
1(
#9200000
0(
#9250000
1(
#9300000
0(
0*
#9350000
1(
#9400000
0(
#9450000
1(
#9500000
0(
#9550000
1(
#9600000
0(
1*
#9650000
1(
#9700000
0(
#9750000
1(
#9800000
0(
0*
